LoopDataConverter/__init__.py
LoopDataConverter/version.py
LoopDataConverter/converters/__init__.py
LoopDataConverter/converters/base_converter.py
LoopDataConverter/converters/conversion_manager.py
LoopDataConverter/converters/ntgs_converter.py
LoopDataConverter/datatypes/__init__.py
LoopDataConverter/datatypes/enums.py
LoopDataConverter/fields/__init__.py
LoopDataConverter/fields/_ntgs/__init__.py
LoopDataConverter/fields/_ntgs/_ntgs_config.py
LoopDataConverter/file_readers/__init__.py
LoopDataConverter/file_readers/_file_readers.py
LoopDataConverter/input/__init__.py
LoopDataConverter/input/input_data.py
LoopDataConverter/utils/__init__.py
LoopDataConverter/utils/conversion.py
tests/__init__.py
tests/converters/__init__.py
tests/file_readers/__init__.py
tests/file_readers/test_file_readers.py
tests/utils/__init__.py
tests/utils/test_conversion.py
LoopDataConverter-0.1.0b0.dist-info/LICENSE
LoopDataConverter-0.1.0b0.dist-info/METADATA
LoopDataConverter-0.1.0b0.dist-info/WHEEL
LoopDataConverter-0.1.0b0.dist-info/top_level.txt
LoopDataConverter-0.1.0b0.dist-info/RECORD
